python_smshub-1.0.0.data/data/my_data/data_file
sample/__init__.py
sample/package_data.dat
python_smshub-1.0.0.dist-info/LICENSE.txt
python_smshub-1.0.0.dist-info/METADATA
python_smshub-1.0.0.dist-info/WHEEL
python_smshub-1.0.0.dist-info/entry_points.txt
python_smshub-1.0.0.dist-info/top_level.txt
python_smshub-1.0.0.dist-info/RECORD
