Metadata-Version: 2.1
Name: python-smshub
Version: 1.0.0
Summary: A sample Python project
Home-page: https://github.com/pypa/sampleproject
Author: The Python Packaging Authority
Author-email: pypa-dev@googlegroups.com
License: UNKNOWN
Project-URL: Bug Reports, https://github.com/pypa/sampleproject/issues
Project-URL: Funding, https://donate.pypi.org
Project-URL: Say Thanks!, http://saythanks.io/to/example
Project-URL: Source, https://github.com/pypa/sampleproject/
Keywords: sample setuptools development
Platform: UNKNOWN
Classifier: Development Status :: 3 - Alpha
Classifier: Intended Audience :: Developers
Classifier: Topic :: Software Development :: Build Tools
Classifier: License :: OSI Approved :: MIT License
Classifier: Programming Language :: Python :: 2
Classifier: Programming Language :: Python :: 2.7
Classifier: Programming Language :: Python :: 3
Classifier: Programming Language :: Python :: 3.4
Classifier: Programming Language :: Python :: 3.5
Classifier: Programming Language :: Python :: 3.6
Classifier: Programming Language :: Python :: 3.7
Requires-Python: >=2.7, !=3.0.*, !=3.1.*, !=3.2.*, !=3.3.*, <4
Requires-Dist: peppercorn
Provides-Extra: dev
Requires-Dist: check-manifest ; extra == 'dev'
Provides-Extra: test
Requires-Dist: coverage ; extra == 'test'
